faquilizer/__init__.py
faquilizer/template.py
faquilizer-0.1.2.dist-info/METADATA
faquilizer-0.1.2.dist-info/WHEEL
faquilizer-0.1.2.dist-info/top_level.txt
faquilizer-0.1.2.dist-info/RECORD
