Metadata-Version: 2.4
Name: faquilizer
Version: 0.1.2
Summary: A Jupyter Notebook template for processing lists of URLs with AI.
Author-email: Mike Levin <pipulate@gmail.com>
License-Expression: MIT
Project-URL: Homepage, https://github.com/miklevin/pipulate
Classifier: Programming Language :: Python :: 3
Classifier: Operating System :: OS Independent
Requires-Python: >=3.8
Requires-Dist: pipulate>=1.2.3
Requires-Dist: google-generativeai
Requires-Dist: requests
Requires-Dist: beautifulsoup4
Requires-Dist: pandas
Requires-Dist: openpyxl
